deepseek_visor_agent/__init__.py
deepseek_visor_agent/device_manager.py
deepseek_visor_agent/infer.py
deepseek_visor_agent/tool.py
deepseek_visor_agent/parsers/__init__.py
deepseek_visor_agent/parsers/base.py
deepseek_visor_agent/parsers/classifier.py
deepseek_visor_agent/parsers/contract.py
deepseek_visor_agent/parsers/invoice.py
deepseek_visor_agent/utils/__init__.py
deepseek_visor_agent/utils/error_handler.py
deepseek_visor_agent/utils/pdf_processor.py
deepseek_visor_agent-0.2.0.dist-info/licenses/LICENSE
deepseek_visor_agent-0.2.0.dist-info/licenses/NOTICE
deepseek_visor_agent-0.2.0.dist-info/METADATA
deepseek_visor_agent-0.2.0.dist-info/WHEEL
deepseek_visor_agent-0.2.0.dist-info/top_level.txt
deepseek_visor_agent-0.2.0.dist-info/RECORD
