Metadata-Version: 2.4
Name: deepseek-visor-agent
Version: 0.2.0
Summary: Production-ready wrapper for DeepSeek-OCR - Convert documents to structured data for AI agents
Author-email: Jack Chen <jack_ai@qq.com>
License: Apache-2.0
Project-URL: Homepage, https://github.com/JackChen-ai/deepseek-visor-agent
Project-URL: Documentation, https://github.com/JackChen-ai/deepseek-visor-agent/blob/main/README.md
Project-URL: Repository, https://github.com/JackChen-ai/deepseek-visor-agent
Project-URL: Issues, https://github.com/JackChen-ai/deepseek-visor-agent/issues
Keywords: deepseek,deepseek-ocr,ocr,ai-agent,langchain,llamaindex,document-understanding,vision-model,document-ocr
Classifier: Development Status :: 3 - Alpha
Classifier: Intended Audience :: Developers
Classifier: License :: OSI Approved :: Apache Software License
Classifier: Programming Language :: Python :: 3
Classifier: Programming Language :: Python :: 3.9
Classifier: Programming Language :: Python :: 3.10
Classifier: Programming Language :: Python :: 3.11
Classifier: Programming Language :: Python :: 3.12
Classifier: Topic :: Software Development :: Libraries :: Python Modules
Classifier: Topic :: Scientific/Engineering :: Artificial Intelligence
Requires-Python: >=3.9
License-File: LICENSE
License-File: NOTICE
Requires-Dist: torch>=2.6.0
Requires-Dist: transformers>=4.46.3
Requires-Dist: tokenizers>=0.20.3
Requires-Dist: einops
Requires-Dist: addict
Requires-Dist: easydict
Requires-Dist: pillow>=10.0.0
Requires-Dist: psutil>=5.9.0
Requires-Dist: pydantic>=2.0.0
Requires-Dist: loguru>=0.7.0
Requires-Dist: PyMuPDF>=1.23.0
Requires-Dist: matplotlib>=3.5.0
Provides-Extra: flash-attn
Requires-Dist: flash-attn==2.7.3; extra == "flash-attn"
Provides-Extra: api
Requires-Dist: fastapi>=0.104.0; extra == "api"
Requires-Dist: uvicorn[standard]>=0.24.0; extra == "api"
Provides-Extra: all
Requires-Dist: flash-attn==2.7.3; extra == "all"
Requires-Dist: fastapi>=0.104.0; extra == "all"
Requires-Dist: uvicorn[standard]>=0.24.0; extra == "all"
Provides-Extra: dev
Requires-Dist: pytest>=7.4.0; extra == "dev"
Requires-Dist: pytest-cov>=4.1.0; extra == "dev"
Requires-Dist: black>=23.0.0; extra == "dev"
Requires-Dist: ruff>=0.1.0; extra == "dev"
Requires-Dist: mypy>=1.5.0; extra == "dev"
Dynamic: license-file
